rockyroad/__init__.py
rockyroad/rockyroad.py
rockyroad/modules/__init__.py
rockyroad/modules/accounts.py
rockyroad/modules/alerts.py
rockyroad/modules/analytics.py
rockyroad/modules/apbs.py
rockyroad/modules/api_info.py
rockyroad/modules/b2c_users.py
rockyroad/modules/business_information.py
rockyroad/modules/calculators.py
rockyroad/modules/case_management.py
rockyroad/modules/companies.py
rockyroad/modules/company_specified_info.py
rockyroad/modules/content_management.py
rockyroad/modules/dealer_parts.py
rockyroad/modules/dealers.py
rockyroad/modules/docs.py
rockyroad/modules/documoto.py
rockyroad/modules/edap.py
rockyroad/modules/emails.py
rockyroad/modules/engines.py
rockyroad/modules/events.py
rockyroad/modules/file_services.py
rockyroad/modules/financials.py
rockyroad/modules/generated_forms.py
rockyroad/modules/information.py
rockyroad/modules/inspections.py
rockyroad/modules/legacy.py
rockyroad/modules/machine_catalog.py
rockyroad/modules/machine_logs.py
rockyroad/modules/machine_passcodes.py
rockyroad/modules/machines.py
rockyroad/modules/module_imports.py
rockyroad/modules/oracle_installed_base_assets.py
rockyroad/modules/oracle_knowledge_management.py
rockyroad/modules/oracle_users.py
rockyroad/modules/parts.py
rockyroad/modules/portal_configurations.py
rockyroad/modules/portal_users.py
rockyroad/modules/predictive_maintenance.py
rockyroad/modules/price_reviews.py
rockyroad/modules/service_reports.py
rockyroad/modules/services.py
rockyroad/modules/sharepoint.py
rockyroad/modules/simple_forms.py
rockyroad/modules/subscriptions.py
rockyroad/modules/summaries.py
rockyroad/modules/tco_calculator.py
rockyroad/modules/technical_content_feedback.py
rockyroad/modules/telematics.py
rockyroad/modules/template.py
rockyroad/modules/users.py
rockyroad/modules/util_data.py
rockyroad/modules/warranties.py
rockyroad/modules/warranty_assessments.py
rockyroad/modules/warranty_configurations.py
rockyroad/modules/warranty_failure_modes.py
rockyroad-0.0.609.dist-info/licenses/LICENSE
rockyroad-0.0.609.dist-info/METADATA
rockyroad-0.0.609.dist-info/WHEEL
rockyroad-0.0.609.dist-info/top_level.txt
rockyroad-0.0.609.dist-info/RECORD
